crowdsec_service_api/__init__.py
crowdsec_service_api/base_model.py
crowdsec_service_api/http_client.py
crowdsec_service_api/models.py
crowdsec_service_api/services/__init__.py
crowdsec_service_api/services/allowlists.py
crowdsec_service_api/services/blocklists.py
crowdsec_service_api/services/hub.py
crowdsec_service_api/services/info.py
crowdsec_service_api/services/integrations.py
crowdsec_service_api/services/metrics.py
crowdsec_service_api-1.69.0.dist-info/licenses/LICENSE
crowdsec_service_api-1.69.0.dist-info/METADATA
crowdsec_service_api-1.69.0.dist-info/WHEEL
crowdsec_service_api-1.69.0.dist-info/top_level.txt
crowdsec_service_api-1.69.0.dist-info/RECORD
